RankCorr/__init__.py
RankCorr/performance.py
RankCorr/rocks.py
markermap/__init__.py
markermap/other_models.py
markermap/smashpy_model.py
markermap/utils.py
markermap/vae_models.py
markermap-1.0.3.dist-info/LICENSE
markermap-1.0.3.dist-info/METADATA
markermap-1.0.3.dist-info/WHEEL
markermap-1.0.3.dist-info/top_level.txt
markermap-1.0.3.dist-info/RECORD
