Metadata-Version: 2.1
Name: markermap
Version: 1.0.3
Summary: Marker selection library for single-cell RNA-seq data
Home-page: https://github.com/Computational-Morphogenomics-Group/MarkerMap
Author: Wilson Gregory, Nabeel Sarwar
Author-email: wilson.g.gregory@gmail.com
Project-URL: Bug Tracker, https://github.com/Computational-Morphogenomics-Group/MarkerMap/issues
Classifier: Programming Language :: Python :: 3
Classifier: License :: OSI Approved :: MIT License
Classifier: Operating System :: OS Independent
Requires-Python: >=3.7
License-File: LICENSE
Requires-Dist: lassonet
Requires-Dist: matplotlib
Requires-Dist: numpy
Requires-Dist: pandas
Requires-Dist: pytorch-lightning >=2.0
Requires-Dist: scanpy
Requires-Dist: seaborn
Requires-Dist: torch
Requires-Dist: umap-learn
Requires-Dist: cosg
